reg/__init__.py
reg/regi.py
regy-2.0.dist-info/LICENCE.txt
regy-2.0.dist-info/METADATA
regy-2.0.dist-info/WHEEL
regy-2.0.dist-info/top_level.txt
regy-2.0.dist-info/RECORD
